quantiletools/__init__.py
quantiletools/quantiles.py
quantiletools-0.1.0.dist-info/licenses/LICENSE.txt
quantiletools-0.1.0.dist-info/METADATA
quantiletools-0.1.0.dist-info/WHEEL
quantiletools-0.1.0.dist-info/top_level.txt
quantiletools-0.1.0.dist-info/RECORD
