Metadata-Version: 2.4
Name: quantiletools
Version: 0.1.0
Summary: Custom quantile calculation tools using Hyndman & Fan (1996) methods.
Home-page: https://github.com/yourusername/quantiletools
Author: Subbiah
Author-email: subbiahbayes@gmail.com
Classifier: Programming Language :: Python :: 3
Classifier: License :: OSI Approved :: MIT License
Classifier: Operating System :: OS Independent
Requires-Python: >=3.6
License-File: LICENSE.txt
Dynamic: author
Dynamic: author-email
Dynamic: classifier
Dynamic: description
Dynamic: description-content-type
Dynamic: home-page
Dynamic: license-file
Dynamic: requires-python
Dynamic: summary
